crypto_accelerator-tessolve/crypto_accelerator-tessolve.srcs/sources_1/new/design.sv
module aes_encrypt (
    input wire clk,
    input wire rst_n,
    input wire start,
    input wire [127:0] plaintext,
    input wire [255:0] key,  // 256-bit AES key
    output reg [127:0] ciphertext,
    output reg done
);

    reg [3:0] state;
    reg [127:0] state_reg;
    reg [255:0] round_key;

    // Updated S-Box: 16-bit values
    reg [15:0] sbox [0:255];
    reg [31:0] rcon [0:9];
    
    // S-Box initialization (partial)
    initial begin
        sbox[8'h00] = 16'h1234; sbox[8'h01] = 16'h5678; sbox[8'h02] = 16'h9abc; sbox[8'h03] = 16'hdef0;
        sbox[8'h04] = 16'h1111; sbox[8'h05] = 16'h2222; sbox[8'h06] = 16'h3333; sbox[8'h07] = 16'h4444;
        // (initialize the rest of the S-Box here)
    end
    
    // Rcon initialization (partial)
    initial begin
        rcon[0] = 32'h01000000;
        rcon[1] = 32'h02000000;
        // (initialize the rest of the Rcon here)
    end
    
    // Key expansion logic (simplified, NAND operation)
    always @(posedge clk or negedge rst_n) begin
        if (!rst_n) begin
            round_key <= key;
        end else if (start) begin
            round_key[127:0] <= ~(round_key[127:0] & {sbox[round_key[23:16]], sbox[round_key[15:8]], sbox[round_key[7:0]], sbox[round_key[31:24]]});
            round_key[255:128] <= ~(round_key[255:128] & rcon[0]);
        end
    end
    
    // AES round logic (simplified, NAND-based encryption)
    always @(posedge clk or negedge rst_n) begin
        if (!rst_n) begin
            state <= 4'd0;
            done <= 1'b0;
        end else if (start) begin
            case (state)
                4'd0: begin
                    state_reg <= ~(plaintext & round_key[127:0]); // Initial round (AddRoundKey using NAND)
                    state <= 4'd1;
                end
                4'd1: begin
                    // S-Box substitution (16-bit wide substitution)
                    state_reg[127:112] <= sbox[state_reg[127:120]];
                    state_reg[111:96]  <= sbox[state_reg[119:112]];
                    state_reg[95:80]   <= sbox[state_reg[111:104]];
                    state_reg[79:64]   <= sbox[state_reg[103:96]];
                    state <= 4'd2;
                end
                4'd2: begin
                    ciphertext <= ~(state_reg & round_key[127:0]); // Final encryption using NAND
                    done <= 1'b1;
                    state <= 4'd0; // Reset state
                end
            endcase
        end
    end
endmodule

crypto_accelerator-tessolve/crypto_accelerator-tessolve.srcs/sim_1/new/testbench.sv
module tb_aes_encrypt;

    // Testbench signals
    reg clk;
    reg rst_n;
    reg start;
    reg [127:0] plaintext;
    reg [255:0] key;  // 256-bit AES key
    wire [127:0] ciphertext;
    wire done;

    // Instantiate the design module
    aes_encrypt uut (
        .clk(clk),
        .rst_n(rst_n),
        .start(start),
        .plaintext(plaintext),
        .key(key),
        .ciphertext(ciphertext),
        .done(done)
    );

    // Clock generation
    always #10 clk = ~clk; // 100 MHz clock
  
    initial begin
        $dumpfile("waveform.vcd"); // Dump waveform to this file
        $dumpvars(0, tb_aes_encrypt); // Dump all variables
    end

    // Test sequence
    initial begin
        // Initialize signals
        clk = 0;
        rst_n = 0;
        start = 0;
        plaintext = 128'h00112233445566778899aabbccddeeff;
        key = 256'h000102030405060708090a0b0c0d0e0f101112131415161718191a1b1c1d1e1f;
        
        // Apply reset
        #100;
        rst_n = 1;

        // Start the encryption process
        #100;
        start = 1;
        #100;
        start = 0;

        // Wait for the encryption to complete
        wait(done);

        // Display the ciphertext
        $display("Ciphertext: %h", ciphertext);

        // End the simulation
        #20;
        $finish;
    end
endmodule

crypto_accelerator-tessolve/crypto_accelerator-tessolve.sim/sim_1/behav/xsim/waveform.vcd
$date
   Fri Dec 13 00:34:52 2024
$end

$version
  2024.2.0
  $dumpfile ("waveform.vcd") 
$end

$timescale
  1ps
$end

$scope module tb_aes_encrypt $end
$var reg 1 ! clk $end
$var reg 1 " rst_n $end
$var reg 1 # start $end
$var reg 128 $ plaintext [127:0] $end
$var reg 256 % key [255:0] $end
$var wire 128 & ciphertext [127:0] $end
$var wire 1 ' done $end
$scope module uut $end
$var wire 1 ( clk $end
$var wire 1 ) rst_n $end
$var wire 1 * start $end
$var wire 128 + plaintext [127:0] $end
$var wire 256 , key [255:0] $end
$var reg 128 - ciphertext [127:0] $end
$var reg 1 . done $end
$var reg 4 / state [3:0] $end
$var reg 128 0 state_reg [127:0] $end
$var reg 256 1 round_key [255:0] $end
$upscope $end
$upscope $end
$enddefinitions $end

#0
$dumpvars
0!
0"
0#
b100010010001000110011010001000101010101100110011101111000100010011001101010101011101111001100110111011110111011111111 $
b1000000100000001100000100000001010000011000000111000010000000100100001010000010110000110000001101000011100000111100010000000100010001001000010011000101000001010100010110000101110001100000011001000110100001101100011100000111010001111000011111 %
bx &
0'
0(
0)
0*
b100010010001000110011010001000101010101100110011101111000100010011001101010101011101111001100110111011110111011111111 +
b1000000100000001100000100000001010000011000000111000010000000100100001010000010110000110000001101000011100000111100010000000100010001001000010011000101000001010100010110000101110001100000011001000110100001101100011100000111010001111000011111 ,
bx -
0.
b0 /
bx 0
b1000000100000001100000100000001010000011000000111000010000000100100001010000010110000110000001101000011100000111100010000000100010001001000010011000101000001010100010110000101110001100000011001000110100001101100011100000111010001111000011111 1
$end

#10000
1!
1(

#20000
0!
0(

#30000
1!
1(

#40000
0!
0(

#50000
1!
1(

#60000
0!
0(

#70000
1!
1(

#80000
0!
0(

#90000
1!
1(

#100000
0!
1"
0(
1)

#110000
1!
1(

#120000
0!
0(

#130000
1!
1(

#140000
0!
0(

#150000
1!
1(

#160000
0!
0(

#170000
1!
1(

#180000
0!
0(

#190000
1!
1(

#200000
0!
1#
0(
1*

#210000
1!
1(
b1 /
b11111111111011101111110111101100111110111110101011111001111010001111011111100110111101011110010011110011111000101111000111100000 0
b111111111111111111111111111111111111111111111111111111111111111111111111111111111111111111111111111111111111111111111111111111111111111111111111111111111111111111111111111111111111111111111111111xx111111xx11x111xx1x1111xx1xx111xxx11111xxx1x111xxxx1111xxxxx 1

#220000
0!
0(

#230000
1!
1(
b10 /
bx1111011111100110111101011110010011110011111000101111000111100000 0
b111111111111111111111111111111111111111111111111111111111111111111111111111111111111111111111111111111101111111111111111111111111111111111111111111111111111111111111111111111111111111111111111xxxxxxxxxxxxxxxxxxxxxxxxxxxxxxxxxxxxxxxxxxxxxxxxxxxxxxxxxxxxxxxx 1

#240000
0!
0(

#250000
1!
bx1xxxxxx11xx1xxxx1x1xxxx11x11xxxx11xxxxx111x1xxxx111xxxx11111 &
1'
1(
bx1xxxxxx11xx1xxxx1x1xxxx11x11xxxx11xxxxx111x1xxxx111xxxx11111 -
1.
b0 /
b111111111111111111111111111111111111111111111111111111111111111111111111111111111111111111111111111111111111111111111111111111111111111111111111111111111111111111111111111111111111111111111111xxxxxxxxxxxxxxxxxxxxxxxxxxxxxxxxxxxxxxxxxxxxxxxxxxxxxxxxxxxxxxxx 1

#260000
0!
0(

#270000
1!
1(
b1 /
b1111111111101110110111011100110010111011101010101001100110001000x111x111x11xx11xx1x1x1x1x1xxx1xxxx11xx11xx1xxx1xxxx1xxx1xxxxxxxx 0
b111111111111111111111111111111111111111111111111111111111111111111111111111111111111111111111111111111101111111111111111111111111111111111111111111111111111111111111111111111111111111111111111xxxxxxxxxxxxxxxxxxxxxxxxxxxxxxxxxxxxxxxxxxxxxxxxxxxxxxxxxxxxxxxx 1

#280000
0!
0(

#290000
1!
1(
b10 /
bx111x111x11xx11xx1x1x1x1x1xxx1xxxx11xx11xx1xxx1xxxx1xxx1xxxxxxxx 0
b111111111111111111111111111111111111111111111111111111111111111111111111111111111111111111111111111111111111111111111111111111111111111111111111111111111111111111111111111111111111111111111111xxxxxxxxxxxxxxxxxxxxxxxxxxxxxxxxxxxxxxxxxxxxxxxxxxxxxxxxxxxxxxxx 1

#300000
0!
0#
0(
0*

